wheel/__init__.py
wheel/__main__.py
wheel/_setuptools_logging.py
wheel/bdist_wheel.py
wheel/macosx_libfile.py
wheel/metadata.py
wheel/util.py
wheel/wheelfile.py
wheel/cli/__init__.py
wheel/cli/convert.py
wheel/cli/pack.py
wheel/cli/unpack.py
wheel/vendored/__init__.py
wheel/vendored/packaging/__init__.py
wheel/vendored/packaging/_manylinux.py
wheel/vendored/packaging/_musllinux.py
wheel/vendored/packaging/tags.py
wheel-0.38.3.dist-info/LICENSE.txt
wheel-0.38.3.dist-info/METADATA
wheel-0.38.3.dist-info/WHEEL
wheel-0.38.3.dist-info/entry_points.txt
wheel-0.38.3.dist-info/top_level.txt
wheel-0.38.3.dist-info/RECORD
