Metadata-Version: 2.1
Name: wheel
Version: 0.38.3
Summary: A built-package format for Python
Home-page: https://github.com/pypa/wheel
Author: Daniel Holth
Author-email: dholth@fastmail.fm
Maintainer: Alex Grönholm
Maintainer-email: alex.gronholm@nextday.fi
License: MIT
Project-URL: Documentation, https://wheel.readthedocs.io/
Project-URL: Changelog, https://wheel.readthedocs.io/en/stable/news.html
Project-URL: Issue Tracker, https://github.com/pypa/wheel/issues
Keywords: wheel,packaging
Classifier: Development Status :: 5 - Production/Stable
Classifier: Intended Audience :: Developers
Classifier: Topic :: System :: Archiving :: Packaging
Classifier: License :: OSI Approved :: MIT License
Classifier: Programming Language :: Python
Classifier: Programming Language :: Python :: 3 :: Only
Classifier: Programming Language :: Python :: 3.7
Classifier: Programming Language :: Python :: 3.8
Classifier: Programming Language :: Python :: 3.9
Classifier: Programming Language :: Python :: 3.10
Classifier: Programming Language :: Python :: 3.11
Requires-Python: >=3.7
Provides-Extra: test
License-File: LICENSE.txt
